{
  "parent": "minecraft:recipes/root",
  "rewards": {
	"recipes": [
	  "techreborn:centrifuge/soul_sand"
	]
  },
  "criteria": {
	"has_soul_sand": {
	  "trigger": "minecraft:inventory_changed",
	  "conditions": {
		"items": [
		  {
			"items": ["minecraft:soul_sand"]
		  }
		]
	  }
	},
	"has_the_recipe": {
	  "trigger": "minecraft:recipe_unlocked",
	  "conditions": {
		"recipe": "techreborn:centrifuge/soul_sand"
	  }
	}
  },
  "requirements": [
	[
	  "has_soul_sand",
	  "has_the_recipe"
	]
  ]
}