{
  "parent": "minecraft:recipes/root",
  "rewards": {
	"recipes": [
	  "techreborn:crafting_table/misc_block/rubber_planks"
	]
  },
  "criteria": {
	"has_rubber_log": {
	  "trigger": "minecraft:inventory_changed",
	  "conditions": {
		"items": [
		  {
			"items": ["techreborn:rubber_log"]
		  }
		]
	  }
	},
	"has_the_recipe": {
	  "trigger": "minecraft:recipe_unlocked",
	  "conditions": {
		"recipe": "techreborn:crafting_table/misc_block/rubber_planks"
	  }
	}
  },
  "requirements": [
	[
	  "has_rubber_log",
	  "has_the_recipe"
	]
  ]
}