{
  "display": {
    "icon": {
      "item": "techreborn:compressor"
    },
    "title": {
      "translate": "advancements.techreborn.compressor"
    },
    "description": {
      "translate": "advancements.techreborn.compressor.desc"
    }
  },
  "parent": "techreborn:machineblock",
  "criteria": {
    "crit1": {
      "trigger": "minecraft:inventory_changed",
      "conditions": {
        "items": [
          {
            "item": "techreborn:compressor"
          }
        ]
      }
    }
  }
}
